SpaTranslator/__init__.py
SpaTranslator/aligner_train.py
SpaTranslator/gat.py
SpaTranslator/graph_align.py
SpaTranslator/spatranslator.py
SpaTranslator/translation_train.py
SpaTranslator/utils.py
spatranslator-1.0.8.dist-info/METADATA
spatranslator-1.0.8.dist-info/WHEEL
spatranslator-1.0.8.dist-info/top_level.txt
spatranslator-1.0.8.dist-info/RECORD
