Metadata-Version: 2.4
Name: SpaTranslator
Version: 1.0.8
Author-email: Sheng Mao <maosheng@westlake.edu.cn>
Project-URL: Homepage, https://github.com/ChrisMao0325/SpaTranslator
Project-URL: Bug Tracker, https://github.com/ChrisMao0325/SpaTranslator/issues
Classifier: Programming Language :: Python :: 3.9
Classifier: License :: OSI Approved :: MIT License
Classifier: Operating System :: POSIX :: Linux
Requires-Python: >=3.9
Requires-Dist: scanpy>=1.9.1
Requires-Dist: torch==2.5.0
Requires-Dist: scikit-learn>=1.1.3
Requires-Dist: scipy==1.9.3
Requires-Dist: episcanpy==0.3.2
Requires-Dist: seaborn>=0.11.2
Requires-Dist: matplotlib>=3.6.2
Requires-Dist: pot==0.9.0
Requires-Dist: torchmetrics==1.6.2
Requires-Dist: leidenalg
Requires-Dist: pybedtools
Requires-Dist: adjusttext
Requires-Dist: jupyter
Requires-Dist: hnswlib
